Metadata-Version: 2.4
Name: bi_code_file
Version: 0.1.0
Summary: A package to download predefined files
Home-page: https://github.com/
Author: Johnny Sins
Classifier: Programming Language :: Python :: 3
Classifier: License :: OSI Approved :: MIT License
Classifier: Operating System :: OS Independent
Requires-Python: >=3.6
Dynamic: author
Dynamic: classifier
Dynamic: description-content-type
Dynamic: home-page
Dynamic: requires-python
Dynamic: summary
